{
  "$schema": "https://mintlify.com/docs.json",
  "name": "Neru",
  "theme": "palm",
  "colors": {
    "primary": "#94cb04",
    "light": "#545454",
    "dark": "#94cb04"
  },
  "favicon": "/logo.png",
  "logo": {
    "light": "/logo.png",
    "dark": "/logo.png"
  },
  "navbar": {
    "primary": {
      "type": "github",
      "href": "https://github.com/y3owk1n/neru"
    }
  },
  "footer": {
    "socials": {
      "github": "https://github.com/y3owk1n/neru"
    }
  },
  "navigation": {
    "tabs": [
      {
        "tab": "Documentation",
        "groups": [
          {
            "group": "Get Started",
            "pages": [
              "introduction",
              "installation",
              "quickstart"
            ]
          },
          {
            "group": "Core Concepts",
            "pages": [
              "concepts/navigation-modes",
              "concepts/recursive-grid",
              "concepts/grid-mode",
              "concepts/hints-mode",
              "concepts/scroll-mode"
            ]
          },
          {
            "group": "Guides",
            "pages": [
              "guides/configuration",
              "guides/hotkeys",
              "guides/mouse-actions",
              "guides/app-exclusions",
              "guides/screen-sharing"
            ]
          },
          {
            "group": "Advanced",
            "pages": [
              "advanced/cli-usage",
              "advanced/scripting",
              "advanced/ipc-automation"
            ]
          },
          {
            "group": "Troubleshooting",
            "pages": [
              "troubleshooting/common-issues",
              "troubleshooting/app-compatibility",
              "troubleshooting/accessibility"
            ]
          }
        ]
      },
      {
        "tab": "Development",
        "groups": [
          {
            "group": "Contributing",
            "pages": [
              "development/overview",
              "development/architecture",
              "development/building",
              "development/coding-standards"
            ]
          },
          {
            "group": "Cross-Platform",
            "pages": [
              "development/cross-platform",
              "development/porting-guide",
              "development/linux-support",
              "development/windows-support"
            ]
          }
        ]
      },
      {
        "tab": "CLI Reference",
        "groups": [
          {
            "group": "Commands",
            "pages": [
              "cli/daemon-control",
              "cli/navigation",
              "cli/actions",
              "cli/services",
              "cli/config"
            ]
          }
        ]
      }
    ]
  }
}
